fabricatio_character/__init__.py
fabricatio_character/config.py
fabricatio_character/py.typed
fabricatio_character/utils.py
fabricatio_character/actions/__init__.py
fabricatio_character/capabilities/__init__.py
fabricatio_character/capabilities/character.py
fabricatio_character/models/__init__.py
fabricatio_character/models/character.py
fabricatio_character/workflows/__init__.py
tests/test_character.py
fabricatio_character-0.1.3.dist-info/METADATA
fabricatio_character-0.1.3.dist-info/WHEEL
fabricatio_character-0.1.3.dist-info/RECORD
