Metadata-Version: 2.4
Name: fabricatio-character
Version: 0.1.3
Summary: An extension of fabricatio
Project-URL: Homepage, https://github.com/Whth/fabricatio
Project-URL: Repository, https://github.com/Whth/fabricatio
Project-URL: Issues, https://github.com/Whth/fabricatio/issues
Author-email: Whth <zettainspector@foxmail.com>
License-Expression: MIT
Classifier: License :: OSI Approved :: MIT License
Classifier: Programming Language :: Python :: 3.12
Classifier: Programming Language :: Python :: 3.13
Classifier: Programming Language :: Python :: 3.14
Classifier: Programming Language :: Python :: Implementation :: CPython
Classifier: Typing :: Typed
Requires-Python: <3.15,>=3.12
Requires-Dist: fabricatio-capabilities
Requires-Dist: fabricatio-core
